Metadata-Version: 1.0
Name: hadoop-ranger-audit
Version: 0.2
Summary: Generates a stand alone web based report for Hadoop Apache Ranger policies.
Home-page: https://github.com/jackscodemonkey/hadoop_ranger_audit
Author: Marcus Robb
Author-email: marcus.robb@initworx.com
License: MIT
Platform: UNKNOWN
